s3fetch/__init__.py
s3fetch/command.py
s3fetch/exceptions.py
s3fetch-1.1.4.dist-info/METADATA
s3fetch-1.1.4.dist-info/entry_points.txt
s3fetch-1.1.4.dist-info/WHEEL
s3fetch-1.1.4.dist-info/LICENSE
s3fetch-1.1.4.dist-info/RECORD
