Metadata-Version: 2.1
Name: s3fetch
Version: 1.1.4
Summary: Simple & fast multi-threaded S3 download tool.
Home-page: https://github.com/rxvt/s3fetch
License: MIT
Keywords: aws,s3
Author: Shane Anderson
Author-email: shane@reactivate.cx
Requires-Python: >=3.7,<4.0
Classifier: License :: OSI Approved :: MIT License
Classifier: Programming Language :: Python :: 3
Classifier: Programming Language :: Python :: 3.7
Classifier: Programming Language :: Python :: 3.8
Classifier: Programming Language :: Python :: 3.9
Classifier: Programming Language :: Python :: 3.10
Classifier: Programming Language :: Python :: 3.11
Requires-Dist: boto3 (>=1.26.63,<2.0.0)
Requires-Dist: click (>=8.0.0,<9.0.0)
Requires-Dist: urllib3 (>=1.26.8,<2.0.0)
Project-URL: Repository, https://github.com/rxvt/s3fetch
